super_scad_polygon/EquilateralTriangle.py
super_scad_polygon/IsoscelesTriangle.py
super_scad_polygon/RegularPolygon.py
super_scad_polygon/RightTriangle.py
super_scad_polygon/SmoothEquilateralTriangle.py
super_scad_polygon/SmoothIsoscelesTriangle.py
super_scad_polygon/SmoothPolygon.py
super_scad_polygon/SmoothPolygonMixin.py
super_scad_polygon/SmoothRectangle.py
super_scad_polygon/SmoothRegularPolygon.py
super_scad_polygon/SmoothRightTriangle.py
super_scad_polygon/SmoothSquare.py
super_scad_polygon/SmoothTriangle.py
super_scad_polygon/Triangle.py
super_scad_polygon/TriangleMixin.py
super_scad_polygon/__init__.py
super_scad_polygon/helper/SmoothPolygonSideExtender.py
super_scad_polygon/helper/__init__.py
super_scad_polygon-0.9.10.dist-info/LICENSE
super_scad_polygon-0.9.10.dist-info/METADATA
super_scad_polygon-0.9.10.dist-info/WHEEL
super_scad_polygon-0.9.10.dist-info/RECORD
